pyombi.py
pyombi-0.1.9.dist-info/LICENSE.txt
pyombi-0.1.9.dist-info/METADATA
pyombi-0.1.9.dist-info/WHEEL
pyombi-0.1.9.dist-info/top_level.txt
pyombi-0.1.9.dist-info/RECORD
