Metadata-Version: 2.1
Name: pyombi
Version: 0.1.9
Summary: A python module to retrieve information from Ombi.
Home-page: https://github.com/larssont/pyombi
Author: Tommy Larsson
Author-email: larssont@tuta.io
License: UNKNOWN
Platform: UNKNOWN
Classifier: Programming Language :: Python :: 3
Classifier: Programming Language :: Python :: 3.7
Classifier: License :: OSI Approved :: MIT License
Classifier: Operating System :: OS Independent
Requires-Dist: requests
